MANIFEST.in
README
setup.cfg
setup.py
hookbox/__init__.py
hookbox/channel.py
hookbox/config.py
hookbox/errors.py
hookbox/log.py
hookbox/output_wrapper.py
hookbox/protocol.py
hookbox/server.py
hookbox/start.py
hookbox/user.py
hookbox/admin/__init__.py
hookbox/admin/admin.py
hookbox/admin/js_src/admin.js
hookbox/admin/static/admin.css
hookbox/admin/static/admin.js
hookbox/admin/static/admin2.js
hookbox/admin/static/highlighter.css
hookbox/admin/static/index.html
hookbox/admin/static/images/h1.png
hookbox/admin/static/images/h3.png
hookbox/admin/static/images/logo.png
hookbox/admin/static/lib/jqueryui/css/overcast/jquery-ui-1.8.custom.css
hookbox/admin/static/lib/jqueryui/css/overcast/images/ui-bg_flat_0_aaaaaa_40x100.png
hookbox/admin/static/lib/jqueryui/css/overcast/images/ui-bg_flat_0_eeeeee_40x100.png
hookbox/admin/static/lib/jqueryui/css/overcast/images/ui-bg_flat_55_c0402a_40x100.png
hookbox/admin/static/lib/jqueryui/css/overcast/images/ui-bg_flat_55_eeeeee_40x100.png
hookbox/admin/static/lib/jqueryui/css/overcast/images/ui-bg_glass_100_f8f8f8_1x400.png
hookbox/admin/static/lib/jqueryui/css/overcast/images/ui-bg_glass_35_dddddd_1x400.png
hookbox/admin/static/lib/jqueryui/css/overcast/images/ui-bg_glass_60_eeeeee_1x400.png
hookbox/admin/static/lib/jqueryui/css/overcast/images/ui-bg_inset-hard_75_999999_1x100.png
hookbox/admin/static/lib/jqueryui/css/overcast/images/ui-bg_inset-soft_50_c9c9c9_1x100.png
hookbox/admin/static/lib/jqueryui/css/overcast/images/ui-icons_3383bb_256x240.png
hookbox/admin/static/lib/jqueryui/css/overcast/images/ui-icons_454545_256x240.png
hookbox/admin/static/lib/jqueryui/css/overcast/images/ui-icons_70b2e1_256x240.png
hookbox/admin/static/lib/jqueryui/css/overcast/images/ui-icons_999999_256x240.png
hookbox/admin/static/lib/jqueryui/css/overcast/images/ui-icons_fbc856_256x240.png
hookbox/admin/static/lib/jqueryui/js/jquery-1.4.2.min.js
hookbox/admin/static/lib/jqueryui/js/jquery-ui-1.8.custom.min.js
hookbox_dax.egg-info/PKG-INFO
hookbox_dax.egg-info/SOURCES.txt
hookbox_dax.egg-info/dependency_links.txt
hookbox_dax.egg-info/entry_points.txt
hookbox_dax.egg-info/not-zip-safe
hookbox_dax.egg-info/requires.txt
hookbox_dax.egg-info/top_level.txt