Metadata-Version: 1.1
Name: hookbox-dax
Version: 0.3.4a1
Summary: HookBox is a Comet server and message queue that tightly integrates with your existing web application via web hooks and a REST interface.
Home-page: https://github.com/raikage/hookbox
Author: Dax Reyes
Author-email: raikage@gmail.com
License: MIT License
Platform: UNKNOWN
Classifier: Development Status :: 4 - Beta
Classifier: Environment :: Console
Classifier: Intended Audience :: Developers
Classifier: License :: OSI Approved :: MIT License
Classifier: Operating System :: OS Independent
Classifier: Programming Language :: Python
Classifier: Topic :: Software Development :: Libraries :: Python Modules
